dendro/__init__.py
dendro/cli.py
dendro/version.txt
dendro/client/__init__.py
dendro/client/submit_job.py
dendro/common/DendroJob.py
dendro/common/__init__.py
dendro/common/api_requests.py
dendro/common/dendro_types.py
dendro/compute_client/ComputeClientDaemon.py
dendro/compute_client/JobManager.py
dendro/compute_client/PubsubClient.py
dendro/compute_client/__init__.py
dendro/compute_client/_start_job.py
dendro/compute_client/register_compute_client.py
dendro/compute_client/run_pending_job.py
dendro/compute_client/start_compute_client.py
dendro/internal_job_monitoring/__init__.py
dendro/internal_job_monitoring/console_output_monitor.py
dendro/internal_job_monitoring/job_status_monitor.py
dendro/internal_job_monitoring/resource_utilization_monitor.py
dendro/internal_job_monitoring/utils.py
dendro/sdk/App.py
dendro/sdk/AppProcessor.py
dendro/sdk/InputFile.py
dendro/sdk/OutputFile.py
dendro/sdk/ProcessorBase.py
dendro/sdk/__init__.py
dendro/sdk/_load_spec_from_uri.py
dendro/sdk/_make_spec_file.py
dendro/sdk/_run_job_child_process.py
dendro/sdk/_run_job_parent_process.py
dendro/sdk/resolve_dandi_url.py
dendro/sdk/upload_additional_job_output.py
dendro-0.6.22.dist-info/METADATA
dendro-0.6.22.dist-info/WHEEL
dendro-0.6.22.dist-info/entry_points.txt
dendro-0.6.22.dist-info/top_level.txt
dendro-0.6.22.dist-info/RECORD
